odoo/addons/base_business_document_import_stock/README.rst
odoo/addons/base_business_document_import_stock/__init__.py
odoo/addons/base_business_document_import_stock/__manifest__.py
odoo/addons/base_business_document_import_stock/i18n/base_business_document_import_stock.pot
odoo/addons/base_business_document_import_stock/models/__init__.py
odoo/addons/base_business_document_import_stock/models/business_document_import.py
odoo/addons/base_business_document_import_stock/static/description/icon.png
odoo/addons/base_business_document_import_stock/tests/__init__.py
odoo/addons/base_business_document_import_stock/tests/test_incoterm_match.py
odoo12_addon_base_business_document_import_stock-12.0.1.0.1.dist-info/METADATA
odoo12_addon_base_business_document_import_stock-12.0.1.0.1.dist-info/WHEEL
odoo12_addon_base_business_document_import_stock-12.0.1.0.1.dist-info/top_level.txt
odoo12_addon_base_business_document_import_stock-12.0.1.0.1.dist-info/RECORD
